<doctrine-mapping xmlns="http://doctrine-project.org/schemas/orm/doctrine-mapping"
                  xmlns:xsi="http://www.w3.org/2001/XMLSchema-instance"
                  xsi:schemaLocation="http://doctrine-project.org/schemas/orm/doctrine-mapping
                    http://doctrine-project.org/schemas/orm/doctrine-mapping.xsd">
    <entity name="DevCtrl\Domain\Item\Property\CustomPossibleValue" table="item_property_possible_values">

        <id name="id" type="integer" column="id">
            <generator strategy="AUTO"/>
            <sequence-generator sequence-name="possiblevalues_autoinc" allocation-size="100" initial-value="1" />
        </id>

        <field name="value" column="value" type="string" length="255" nullable="false" unique="false" />
        <field name="order" column="`order`" type="integer" nullable="true" unique="false" />

        <one-to-one field="property" target-entity="DevCtrl\Domain\Item\Property">
            <join-column name="item_property_id" referenced-column-name="id" />
        </one-to-one>

    </entity>
</doctrine-mapping>